thonnycontrib/__init__.py
thonnycontrib/gitonic/__init__.py
thonny_gitonic-0.0.2.dist-info/LICENSE.md
thonny_gitonic-0.0.2.dist-info/METADATA
thonny_gitonic-0.0.2.dist-info/WHEEL
thonny_gitonic-0.0.2.dist-info/top_level.txt
thonny_gitonic-0.0.2.dist-info/RECORD
