Metadata-Version: 2.1
Name: thonny-gitonic
Version: 0.0.2
Summary: manage a multi git workspace
Home-page: https://github.com/kr-g/thonny-gitonic
Author: k.r. goger
Author-email: k.r.goger+thonny-gitonic@gmail.com
License: MIT
Keywords: python utility shell git git-workspace tkinter thonny
Platform: UNKNOWN
Classifier: Development Status :: 3 - Alpha
Classifier: Operating System :: POSIX :: Linux
Classifier: Environment :: Console
Classifier: Environment :: Other Environment
Classifier: Intended Audience :: Developers
Classifier: Topic :: Utilities
Classifier: Topic :: Desktop Environment
Classifier: Programming Language :: Python :: 3
Classifier: License :: OSI Approved :: GNU Affero General Public License v3 or later (AGPLv3+)
Requires-Python: >=3.8
License-File: LICENSE.md
Requires-Dist: gitonic
Requires-Dist: thonny (>=3.3.0)
